ftw/__init__.py
ftw/datamodules.py
ftw/datasets.py
ftw/metrics.py
ftw/trainers.py
ftw/utils.py
ftw/models/__init__.py
ftw/models/delineate_anything.py
ftw_cli/__init__.py
ftw_cli/cfg.py
ftw_cli/cli.py
ftw_cli/download_ftw.py
ftw_cli/download_img.py
ftw_cli/inference.py
ftw_cli/lulc_filtering.py
ftw_cli/model.py
ftw_cli/polygonize.py
ftw_cli/types.py
ftw_cli/unpack.py
ftw_tools-1.4.3.dist-info/licenses/LICENSE
tests/test_data.py
tests/test_help.py
tests/test_inference.py
tests/test_model.py
tests/test_models.py
tests/test_utils.py
ftw_tools-1.4.3.dist-info/METADATA
ftw_tools-1.4.3.dist-info/WHEEL
ftw_tools-1.4.3.dist-info/entry_points.txt
ftw_tools-1.4.3.dist-info/top_level.txt
ftw_tools-1.4.3.dist-info/RECORD
