Metadata-Version: 2.4
Name: ftw-tools
Version: 1.4.3
Summary: Fields of The World (FTW) Command Line Interface (CLI) for data management, ML processing, and more.
Author-email: Hannah Kerner <hkerner@asu.edu>, Matthias Mohr <matthias@mohr.ws>, Caleb Robinson <Caleb.Robinson@microsoft.com>, Aninda Ghosh <aghosh57@asu.edu>, Chris Holmes <cholmes@tgengine.org>, Snehal Chaudhari <sschaud5@asu.edu>
License-Expression: MIT
Project-URL: Homepage, https://fieldsofthe.world/
Project-URL: Repository, https://github.com/fieldsoftheworld/ftw-baselines.git
Project-URL: Issues, https://github.com/fieldsoftheworld/ftw-baselines/issues
Project-URL: Changelog, https://github.com/fieldsoftheworld/ftw-baselines/blob/main/CHANGELOG.md
Classifier: Development Status :: 4 - Beta
Classifier: Programming Language :: Python :: 3
Requires-Python: <3.13,>=3.11
License-File: LICENSE
Requires-Dist: click
Requires-Dist: tqdm
Requires-Dist: geopandas
Requires-Dist: rasterio
Requires-Dist: numpy
Requires-Dist: matplotlib
Requires-Dist: torch
Requires-Dist: kornia
Requires-Dist: torchvision
Requires-Dist: pytorch-lightning
Requires-Dist: PyYAML
Requires-Dist: wget
Requires-Dist: pyarrow==16.1.0
Requires-Dist: odc-stac>=0.4.0
Requires-Dist: planetary-computer
Requires-Dist: pystac
Requires-Dist: rioxarray
Requires-Dist: scipy
Requires-Dist: tensorboard
Requires-Dist: torchgeo>=0.7.0
Requires-Dist: fiona
Requires-Dist: pyproj
Requires-Dist: fiboa-cli==0.7.0
Requires-Dist: tenacity==9.1.2
Requires-Dist: dask[distributed]==2025.5.1
Provides-Extra: delineate-anything
Requires-Dist: ultralytics<9.0,>8.3.0; extra == "delineate-anything"
Provides-Extra: dev
Requires-Dist: ruff; extra == "dev"
Requires-Dist: pytest; extra == "dev"
Provides-Extra: all
Requires-Dist: ftw-tools[delineate-anything,dev]; extra == "all"
Dynamic: license-file
